bls/__init__.py
bls/api.py
bls-0.3.0.dist-info/METADATA
bls-0.3.0.dist-info/RECORD
bls-0.3.0.dist-info/WHEEL
bls-0.3.0.dist-info/top_level.txt
